trimnet_drug/__init__.py
trimnet-1.0.8.dist-info/LICENSE
trimnet-1.0.8.dist-info/METADATA
trimnet-1.0.8.dist-info/WHEEL
trimnet-1.0.8.dist-info/top_level.txt
trimnet-1.0.8.dist-info/RECORD
