Metadata-Version: 2.1
Name: trimnet
Version: 1.0.8
Summary: Your library description
Author: Your Name
License-File: LICENSE
Requires-Dist: torch-geometric (==2.3.1)
Requires-Dist: pandas (==2.0.2)
Requires-Dist: rdkit (==2023.3.1)
Requires-Dist: bump2version
Requires-Dist: torch
Requires-Dist: torchvision
Requires-Dist: torchaudio
